MANIFEST.in
README.md
setup.py
cutkum/__init__.py
cutkum/best2010_reader.py
cutkum/char_dictionary.py
cutkum/ck_model.py
cutkum/command_line.py
cutkum/freeze_graph.py
cutkum/frozen_model.pb
cutkum/sequence_handler.py
cutkum/tokenizer.py
cutkum/train.py
cutkum/util.py
cutkum.egg-info/PKG-INFO
cutkum.egg-info/SOURCES.txt
cutkum.egg-info/dependency_links.txt
cutkum.egg-info/entry_points.txt
cutkum.egg-info/requires.txt
cutkum.egg-info/top_level.txt
cutkum.egg-info/zip-safe