Metadata-Version: 1.0
Name: cutkum
Version: 2.4
Summary: Thai Word-Segmentation with LSTM in Tensorflow
Home-page: https://github.com/pucktada/cutkum
Author: Puck Treeratpituk
Author-email: pucktada@gmail.com
License: MIT
Keywords: thai tokenizer tensorflow lstm
Platform: UNKNOWN
